MANIFEST.in
setup.cfg
setup.py
hummus.egg-info/PKG-INFO
hummus.egg-info/SOURCES.txt
hummus.egg-info/dependency_links.txt
hummus.egg-info/requires.txt
hummus.egg-info/top_level.txt
lib/python/interface/PythonByteReader.cxx
lib/python/interface/PythonByteReader.h
lib/python/interface/PythonByteReaderWithPosition.cxx
lib/python/interface/PythonByteReaderWithPosition.h
lib/python/interface/PythonByteWriter.cxx
lib/python/interface/PythonByteWriter.h
lib/python/interface/PythonByteWriterWithPosition.cxx
lib/python/interface/PythonByteWriterWithPosition.h
src/hummus/__init__.py
src/hummus/context.pxd
src/hummus/context.pyx
src/hummus/document.py
src/hummus/font.py
src/hummus/image.pxd
src/hummus/image.pyx
src/hummus/interface.pxd
src/hummus/interface.pyx
src/hummus/meta.py
src/hummus/page.pxd
src/hummus/page.pyx
src/hummus/reader.pxd
src/hummus/reader.pyx
src/hummus/rectangle.pxd
src/hummus/rectangle.pyx
src/hummus/stream.py
src/hummus/text.pyx
src/hummus/utils.pxd
src/hummus/writer.pxd
src/hummus/writer.pyx