Metadata-Version: 1.1
Name: hummus
Version: 0.3.15
Summary: Pythonic API for hummus, the fast and free PDF reader / writer.
Home-page: https://github.com/concordusapps/python-hummus
Author: Concordus Applications
Author-email: support@concordusapps.com
License: UNKNOWN
Platform: UNKNOWN
Classifier: Development Status :: 3 - Alpha
Classifier: Intended Audience :: Developers
Classifier: Intended Audience :: System Administrators
Classifier: License :: OSI Approved :: MIT License
Classifier: Operating System :: OS Independent
Classifier: Programming Language :: Python :: 3.3
